LICENSE
MANIFEST.in
README.md
setup.py
hacs_frontend/__init__.py
hacs_frontend/entrypoint.js
hacs_frontend/extra.js
hacs_frontend/version.py
hacs_frontend/frontend_es5/1010.AR3RIkMATco.js
hacs_frontend/frontend_es5/1010.AR3RIkMATco.js.gz
hacs_frontend/frontend_es5/1010.AR3RIkMATco.js.map
hacs_frontend/frontend_es5/1021.HaKB3Xh9nXM.js
hacs_frontend/frontend_es5/1021.HaKB3Xh9nXM.js.gz
hacs_frontend/frontend_es5/1021.HaKB3Xh9nXM.js.map
hacs_frontend/frontend_es5/1044.ycJ_S_A2-kU.js
hacs_frontend/frontend_es5/1044.ycJ_S_A2-kU.js.gz
hacs_frontend/frontend_es5/1044.ycJ_S_A2-kU.js.map
hacs_frontend/frontend_es5/1054.2sGa23u2BVA.js
hacs_frontend/frontend_es5/1054.2sGa23u2BVA.js.gz
hacs_frontend/frontend_es5/1054.2sGa23u2BVA.js.map
hacs_frontend/frontend_es5/1122.cRZfhVfBaKw.js
hacs_frontend/frontend_es5/1122.cRZfhVfBaKw.js.gz
hacs_frontend/frontend_es5/1122.cRZfhVfBaKw.js.map
hacs_frontend/frontend_es5/1159.hP_ifuQefsk.js
hacs_frontend/frontend_es5/1159.hP_ifuQefsk.js.LICENSE.txt
hacs_frontend/frontend_es5/1159.hP_ifuQefsk.js.gz
hacs_frontend/frontend_es5/1159.hP_ifuQefsk.js.map
hacs_frontend/frontend_es5/1184.Jc9DlzM6trU.js
hacs_frontend/frontend_es5/1184.Jc9DlzM6trU.js.gz
hacs_frontend/frontend_es5/1184.Jc9DlzM6trU.js.map
hacs_frontend/frontend_es5/1258.iEXY48kicws.js
hacs_frontend/frontend_es5/1258.iEXY48kicws.js.gz
hacs_frontend/frontend_es5/1258.iEXY48kicws.js.map
hacs_frontend/frontend_es5/1260.H52AsJvUcqQ.js
hacs_frontend/frontend_es5/1260.H52AsJvUcqQ.js.LICENSE.txt
hacs_frontend/frontend_es5/1260.H52AsJvUcqQ.js.gz
hacs_frontend/frontend_es5/1260.H52AsJvUcqQ.js.map
hacs_frontend/frontend_es5/1267.PSNG9Xy-FLU.js
hacs_frontend/frontend_es5/1267.PSNG9Xy-FLU.js.gz
hacs_frontend/frontend_es5/1267.PSNG9Xy-FLU.js.map
hacs_frontend/frontend_es5/1379.YjnMNiIaItA.js
hacs_frontend/frontend_es5/1379.YjnMNiIaItA.js.gz
hacs_frontend/frontend_es5/1379.YjnMNiIaItA.js.map
hacs_frontend/frontend_es5/14.fGk1i5_aZmA.js
hacs_frontend/frontend_es5/14.fGk1i5_aZmA.js.LICENSE.txt
vps_frontend.egg-info/PKG-INFO
vps_frontend.egg-info/SOURCES.txt
vps_frontend.egg-info/dependency_links.txt
vps_frontend.egg-info/not-zip-safe
vps_frontend.egg-info/top_level.txt