Metadata-Version: 2.1
Name: vps-frontend
Version: 20240903140523
Summary: The VPS frontend
Home-page: https://github.com/Vioneta/vps-frontend
Author: Vioneta
Author-email: admin@vioneta.com
License-File: LICENSE
